src/ALU.v
module ALU (
    input wire [31:0] a,
    input wire [31:0] b,
    input wire [9:0]  alu_ctrl, // 10 bit theo đồ án
    output reg [31:0] result,
    output wire       zero
);
    always @(*) begin
        case (alu_ctrl)
            10'b0000000001: result = a + b;                   // Bit 0: ADD
            10'b0000000010: result = a - b;                   // Bit 1: SUB
            10'b0000000100: result = a << b[4:0];             // Bit 2: SLL
            10'b0000001000: result = ($signed(a) < $signed(b)); // Bit 3: SLT
            10'b0000010000: result = (a < b);                 // Bit 4: SLTU
            10'b0000100000: result = a ^ b;                   // Bit 5: XOR
            10'b0001000000: result = a >> b[4:0];             // Bit 6: SRL
            10'b0010000000: result = a >>> b[4:0];            // Bit 7: SRA
            10'b0100000000: result = a | b;                   // Bit 8: OR
            10'b1000000000: result = a & b;                   // Bit 9: AND
            default: result = 32'b0;
        endcase
    end
    assign zero = (result == 32'b0);
endmodule

testbench/ALU_tb.v
`timescale 1ns/1ps

module ALU_tb;
    reg [31:0] a;
    reg [31:0] b;
    reg [9:0]  alu_ctrl;
    wire [31:0] result;
    wire        zero;

    ALU uut (
        .a(a),
        .b(b),
        .alu_ctrl(alu_ctrl),
        .result(result),
        .zero(zero)
    );

    initial begin
        $dumpfile("mophong_vcd/ALU_tb.vcd");
        $dumpvars(0, ALU_tb);

        a = 32'h0000_0005; b = 32'h0000_0003;

        // ADD
        alu_ctrl = 10'b0000000001; #10;
        if (result !== 32'h8) $display("ERROR ADD: expected 8, got %h", result);

        // SUB
        alu_ctrl = 10'b0000000010; #10;
        if (result !== 32'h2) $display("ERROR SUB: expected 2, got %h", result);

        // SLL
        alu_ctrl = 10'b0000000100; #10;
        if (result !== 32'h0000_0080) $display("ERROR SLL: expected 0x80, got %h", result);

        // SLT
        alu_ctrl = 10'b0000001000; #10;
        if (result !== 32'h0000_0000) $display("ERROR SLT: expected 0, got %h", result);

        // SLTU
        alu_ctrl = 10'b0000010000; #10;
        if (result !== 32'h0000_0000) $display("ERROR SLTU: expected 0, got %h", result);

        // XOR
        alu_ctrl = 10'b0000100000; #10;
        if (result !== 32'h0000_0006) $display("ERROR XOR: expected 6, got %h", result);

        // SRL
        alu_ctrl = 10'b0001000000; #10;
        if (result !== 32'h0000_0000) $display("ERROR SRL: expected 0, got %h", result);

        // SRA
        a = 32'hFFFF_FFF8; b = 32'h0000_0002;
        alu_ctrl = 10'b0010000000; #10;
        if (result !== 32'hFFFF_FFFE) $display("ERROR SRA: expected FFFE, got %h", result);

        // OR
        a = 32'h0000_F0F0; b = 32'h0000_0F0F;
        alu_ctrl = 10'b0100000000; #10;
        if (result !== 32'h0000_FFFF) $display("ERROR OR: expected FFFF, got %h", result);

        // AND
        alu_ctrl = 10'b1000000000; #10;
        if (result !== 32'h0000_0000) $display("ERROR AND: expected 0, got %h", result);

        $display("ALU_tb finished");
        $finish;
    end
endmodule

mophong_vcd/ALU_tb.vcd
$date
	Fri Apr 17 23:04:21 2026
$end
$version
	Icarus Verilog
$end
$timescale
	1ps
$end
$scope module ALU_tb $end
$var wire 1 ! zero $end
$var wire 32 " result [31:0] $end
$var reg 32 # a [31:0] $end
$var reg 10 $ alu_ctrl [9:0] $end
$var reg 32 % b [31:0] $end
$scope module uut $end
$var wire 32 & a [31:0] $end
$var wire 10 ' alu_ctrl [9:0] $end
$var wire 32 ( b [31:0] $end
$var wire 1 ! zero $end
$var reg 32 ) result [31:0] $end
$upscope $end
$upscope $end
$enddefinitions $end
$comment Show the parameter values. $end
$dumpall
$end
#0
$dumpvars
b1000 )
b11 (
b1 '
b101 &
b11 %
b1 $
b101 #
b1000 "
0!
$end
#10000
b10 "
b10 )
b10 $
b10 '
#20000
b101000 "
b101000 )
b100 $
b100 '
#30000
1!
b0 "
b0 )
b1000 $
b1000 '
#40000
b10000 $
b10000 '
#50000
0!
b110 "
b110 )
b100000 $
b100000 '
#60000
1!
b0 "
b0 )
b1000000 $
b1000000 '
#70000
0!
b111111111111111111111111111110 "
b111111111111111111111111111110 )
b10000000 $
b10000000 '
b10 %
b10 (
b11111111111111111111111111111000 #
b11111111111111111111111111111000 &
#80000
b1111111111111111 "
b1111111111111111 )
b100000000 $
b100000000 '
b111100001111 %
b111100001111 (
b1111000011110000 #
b1111000011110000 &
#90000
1!
b0 "
b0 )
b1000000000 $
b1000000000 '
