src/ALU.v
module ALU (
    input wire [31:0] a,
    input wire [31:0] b,
    input wire [3:0]  alu_ctrl, 
    output reg [31:0] result,
    output wire       zero
);
    always @(*) begin
        case (alu_ctrl)
            4'b0000: result = a + b;                     // ADD
            4'b0001: result = a - b;                     // SUB
            4'b0010: result = a << b[4:0];               // SLL
            4'b0011: result = ($signed(a) < $signed(b)) ? 32'd1 : 32'd0; // SLT (Đảm bảo trả về đúng format 32-bit)
            4'b0100: result = (a < b) ? 32'd1 : 32'd0;   // SLTU
            4'b0101: result = a ^ b;                     // XOR
            4'b0110: result = a >> b[4:0];               // SRL
            4'b0111: result = $signed(a) >>> b[4:0];      // SRA
            4'b1000: result = a | b;                     // OR
            4'b1001: result = a & b;                     // AND
            4'b1010: result = b;                         // LUI: Lấy thẳng giá trị b (Immediate)
            default: result = 32'b0;
        endcase
    end
    //moi
    assign zero = (result == 32'b0);
endmodule

testbench/ALU_tb.v
`timescale 1ns/1ps

module ALU_tb;
    reg [31:0] a;
    reg [31:0] b;
    reg [10:0]  alu_ctrl;
    wire [31:0] result;
    wire        zero;

    ALU uut (
        .a(a),
        .b(b),
        .alu_ctrl(alu_ctrl),
        .result(result),
        .zero(zero)
    );

    task check;
        input [31:0] expected;
        input [9:0]  op;
        input [31:0]  exp_zero;
        begin
            #10;
            if (result !== expected) $display("ERROR %b: expected %h, got %h", op, expected, result);
            if (zero !== exp_zero) $display("ERROR %b zero: expected %b, got %b", op, exp_zero, zero);
        end
    endtask

    initial begin
        $dumpfile("mophong_vcd/ALU_tb.vcd");
        $dumpvars(0, ALU_tb);
        $monitor("t=%0t alu_ctrl=%b a=%h b=%h result=%h zero=%b",
                 $time, alu_ctrl, a, b, result, zero);

        // ADD
        a = 32'h0000_0005; b = 32'h0000_0003;
        alu_ctrl = 11'b00000000001; check(32'h0000_0008, alu_ctrl, 1'b0);

        // ADD zero
        a = 32'h0000_0007; b = 32'hFFFF_FFF9;
        alu_ctrl = 11'b00000000001; check(32'h0000_0000, alu_ctrl, 1'b1);

        // SUB
        a = 32'h0000_0005; b = 32'h0000_0003;
        alu_ctrl = 11'b00000000010; check(32'h0000_0002, alu_ctrl, 1'b0);

        // SUB zero
        a = 32'h0000_00AA; b = 32'h0000_00AA;
        alu_ctrl = 11'b00000000010; check(32'h0000_0000, alu_ctrl, 1'b1);

        // SLL
        a = 32'h0000_0001; b = 32'h0000_0005;
        alu_ctrl = 11'b00000000100; check(32'h0000_0020, alu_ctrl, 1'b0);

        // SLT signed less
        a = 32'hFFFF_FFFF; b = 32'h0000_0001;
        alu_ctrl = 11'b00000001000; check(32'h0000_0001, alu_ctrl, 1'b0);

        // SLT signed greater
        a = 32'h0000_0002; b = 32'hFFFF_FFFF;
        alu_ctrl = 11'b00000001000; check(32'h0000_0000, alu_ctrl, 1'b1);

        // SLTU unsigned less
        a = 32'h0000_0001; b = 32'h0000_0002;
        alu_ctrl = 11'b00000010000; check(32'h0000_0001, alu_ctrl, 1'b0);

        // SLTU unsigned greater
        a = 32'hFFFF_FFFF; b = 32'h0000_0000;
        alu_ctrl = 11'b00000010000; check(32'h0000_0000, alu_ctrl, 1'b1);

        // XOR
        a = 32'h1234_5678; b = 32'hFFFF_0000;
        alu_ctrl = 11'b00000100000; check(32'hEDCB_5678, alu_ctrl, 1'b0);

        // SRL logical right shift
        a = 32'h8000_0000; b = 32'h0000_0001;
        alu_ctrl = 11'b00001000000; check(32'h4000_0000, alu_ctrl, 1'b0);

        // SRL zero result
        a = 32'h0000_0001; b = 32'h0000_0001;
        alu_ctrl = 11'b00001000000; check(32'h0000_0000, alu_ctrl, 1'b1);

        // SRA arithmetic right shift negative
        a = 32'hFFFF_FFF8; b = 32'h0000_0002;
        alu_ctrl = 11'b00010000000; check(32'hFFFF_FFFE, alu_ctrl, 1'b0);

        // SRA arithmetic right shift positive
        a = 32'h0000_0008; b = 32'h0000_0002;
        alu_ctrl = 11'b00010000000; check(32'h0000_0002, alu_ctrl, 1'b0);

        // OR
        a = 32'h0000_F0F0; b = 32'h0000_0F0F;
        alu_ctrl = 11'b00100000000; check(32'h0000_FFFF, alu_ctrl, 1'b0);

        // AND
        a = 32'h0000_F0F0; b = 32'h0000_0F0F;
        alu_ctrl = 11'b01000000000; check(32'h0000_0000, alu_ctrl, 1'b1);

        $display("ALU_tb finished");
        $finish;
    end
endmodule

mophong_vcd/ALU_tb.vcd
$date
	Mon Jun  8 23:44:16 2026
$end
$version
	Icarus Verilog
$end
$timescale
	1ps
$end
$scope module ALU_tb $end
$var wire 1 ! zero $end
$var wire 32 " result [31:0] $end
$var reg 32 # a [31:0] $end
$var reg 11 $ alu_ctrl [10:0] $end
$var reg 32 % b [31:0] $end
$scope module uut $end
$var wire 32 & a [31:0] $end
$var wire 4 ' alu_ctrl [3:0] $end
$var wire 32 ( b [31:0] $end
$var wire 1 ! zero $end
$var reg 32 ) result [31:0] $end
$upscope $end
$scope task check $end
$var reg 32 * exp_zero [31:0] $end
$var reg 32 + expected [31:0] $end
$var reg 10 , op [9:0] $end
$upscope $end
$upscope $end
$enddefinitions $end
$comment Show the parameter values. $end
$dumpall
$end
#0
$dumpvars
b1 ,
b1000 +
b0 *
b10 )
b11 (
b1 '
b101 &
b11 %
b1 $
b101 #
b10 "
0!
$end
#10000
b1110 "
b1110 )
b1 *
b0 +
b11111111111111111111111111111001 %
b11111111111111111111111111111001 (
b111 #
b111 &
#20000
b10 '
b101000 "
b101000 )
b0 *
b10 ,
b10 +
b10 $
b11 %
b11 (
b101 #
b101 &
#30000
b101010100000000000 "
b101010100000000000 )
b1 *
b0 +
b10101010 %
b10101010 (
b10101010 #
b10101010 &
#40000
b100 '
b1 "
b1 )
b0 *
b100 ,
b100000 +
b100 $
b101 %
b101 (
b1 #
b1 &
#50000
b1000 '
0!
b11111111111111111111111111111111 "
b11111111111111111111111111111111 )
b1000 ,
b1 +
b1000 $
b1 %
b1 (
b11111111111111111111111111111111 #
b11111111111111111111111111111111 &
#60000
b1 *
b0 +
b11111111111111111111111111111111 %
b11111111111111111111111111111111 (
b10 #
b10 &
#70000
b0 '
b11 "
b11 )
b0 *
b10000 ,
b1 +
b10000 $
b10 %
b10 (
b1 #
b1 &
#80000
b11111111111111111111111111111111 "
b11111111111111111111111111111111 )
b1 *
b0 +
b0 %
b0 (
b11111111111111111111111111111111 #
b11111111111111111111111111111111 &
#90000
b10010001100110101011001111000 "
b10010001100110101011001111000 )
b0 *
b100000 ,
b11101101110010110101011001111000 +
b100000 $
b11111111111111110000000000000000 %
b11111111111111110000000000000000 (
b10010001101000101011001111000 #
b10010001101000101011001111000 &
#100000
b10000000000000000000000000000001 "
b10000000000000000000000000000001 )
b1000000 ,
b1000000000000000000000000000000 +
b1000000 $
b1 %
b1 (
b10000000000000000000000000000000 #
b10000000000000000000000000000000 &
#110000
b10 "
b10 )
b1 *
b0 +
b1 #
b1 &
#120000
b11111111111111111111111111111010 "
b11111111111111111111111111111010 )
b0 *
b10000000 ,
b11111111111111111111111111111110 +
b10000000 $
b10 %
b10 (
b11111111111111111111111111111000 #
b11111111111111111111111111111000 &
#130000
b1010 "
b1010 )
b10 +
b1000 #
b1000 &
#140000
b1111111111111111 "
b1111111111111111 )
b100000000 ,
b1111111111111111 +
b100000000 $
b111100001111 %
b111100001111 (
b1111000011110000 #
b1111000011110000 &
#150000
b1 *
b1000000000 ,
b0 +
b1000000000 $
