src/control_unit.v
module control_unit (
    input wire [6:0] opcode,
    input wire [2:0] funct3,
    input wire [6:0] funct7, // funct7[5] là bit thứ 30 của lệnh

    output reg        regWrite_D,   // Cho phép ghi vào Reg File
    output reg [2:0]  imm_sel,      // Chọn kiểu mở rộng hằng số
    output reg        alu_srcA_D,   // Chọn đầu vào A cho ALU (0: rs1, 1: PC)
    output reg        alu_srcB_D,   // Chọn đầu vào B cho ALU (0: rs2, 1: Imm)
    output reg [9:0]  alu_ctrl,     // 10-bit One-hot điều khiển phép toán ALU
    output reg        branch_D,     // Báo hiệu lệnh rẽ nhánh (đi vào bộ dự đoán)
    output reg [2:0]  bropcode,     // Loại rẽ nhánh (BEQ, BNE, BLT...)
    output reg [1:0]  jump_D,       // Loại nhảy (00: No, 01: JAL, 10: JALR)
    output reg [2:0]  load_sel_D,   // Kiểu Load (LB, LH, LW...)
    output reg [2:0]  store_sel_D,  // Kiểu Store (SB, SH, SW)
    output reg        memWrite_D,   // Cho phép ghi bộ nhớ
    output reg [1:0]  write_back_D  // Chọn kết quả về WB (00:ALU, 01:Mem, 10:PC+4)
);

    // Định nghĩa hằng số ALU One-hot
    localparam ALU_ADD  = 10'b0000000001;
    localparam ALU_SUB  = 10'b0000000010;
    localparam ALU_SLL  = 10'b0000000100;
    localparam ALU_SLT  = 10'b0000001000;
    localparam ALU_SLTU = 10'b0000010000;
    localparam ALU_XOR  = 10'b0000100000;
    localparam ALU_SRL  = 10'b0001000000;
    localparam ALU_SRA  = 10'b0010000000;
    localparam ALU_OR   = 10'b0100000000;
    localparam ALU_AND  = 10'b1000000000;

    always @(*) begin
        // --- Mặc định ---
        regWrite_D = 0; imm_sel = 3'b000; alu_srcA_D = 0; alu_srcB_D = 0;
        alu_ctrl = ALU_ADD; branch_D = 0; bropcode = 3'b000; jump_D = 2'b00;
        load_sel_D = 3'b010; store_sel_D = 3'b010; memWrite_D = 0; write_back_D = 2'b00;

        case (opcode)
            // 1. LUI (Load Upper Immediate)
            7'b0110111: begin
                regWrite_D = 1; imm_sel = 3'b011; alu_srcB_D = 1;
                alu_ctrl = ALU_ADD; // ALU tính x0 + Imm (rs1 lúc này là x0)
                write_back_D = 2'b00;
            end

            // 2. AUIPC (Add Upper Imm to PC)
            7'b0010111: begin
                regWrite_D = 1; imm_sel = 3'b011; alu_srcA_D = 1; alu_srcB_D = 1;
                alu_ctrl = ALU_ADD; // PC + Imm
                write_back_D = 2'b00;
            end

            // 3. JAL (Jump and Link)
            7'b1101111: begin
                regWrite_D = 1; imm_sel = 3'b100; jump_D = 2'b01;
                write_back_D = 2'b10; // Lưu PC+4 vào rd
            end

            // 4. JALR (Jump and Link Register)
            7'b1100111: begin
                regWrite_D = 1; imm_sel = 3'b000; jump_D = 2'b10;
                alu_srcB_D = 1; alu_ctrl = ALU_ADD; // rs1 + Imm
                write_back_D = 2'b10;
            end

            // 5-10. BRANCH (6 lệnh: BEQ, BNE, BLT, BGE, BLTU, BGEU)
            7'b1100011: begin
                branch_D = 1; imm_sel = 3'b010; bropcode = funct3;
                alu_ctrl = (funct3[2:1] == 2'b11) ? ALU_SLTU : ALU_SUB; 
            end

            // 11-15. LOAD (5 lệnh: LB, LH, LW, LBU, LHU)
            7'b0000011: begin
                regWrite_D = 1; imm_sel = 3'b000; alu_srcB_D = 1;
                alu_ctrl = ALU_ADD; load_sel_D = funct3; write_back_D = 2'b01;
            end

            // 16-18. STORE (3 lệnh: SB, SH, SW)
            7'b0100011: begin
                memWrite_D = 1; imm_sel = 3'b001; alu_srcB_D = 1;
                alu_ctrl = ALU_ADD; store_sel_D = funct3;
            end

            // 19-27. I-Type ALU (9 lệnh: ADDI, SLTI, SLTIU, XORI, ORI, ANDI, SLLI, SRLI, SRAI)
            7'b0010011: begin
                regWrite_D = 1; alu_srcB_D = 1; imm_sel = 3'b000;
                case (funct3)
                    3'b000: alu_ctrl = ALU_ADD;
                    3'b010: alu_ctrl = ALU_SLT;
                    3'b011: alu_ctrl = ALU_SLTU;
                    3'b100: alu_ctrl = ALU_XOR;
                    3'b110: alu_ctrl = ALU_OR;
                    3'b111: alu_ctrl = ALU_AND;
                    3'b001: alu_ctrl = ALU_SLL;
                    3'b101: alu_ctrl = (funct7[5]) ? ALU_SRA : ALU_SRL;
                endcase
            end

            // 28-37. R-Type ALU (10 lệnh: ADD, SUB, SLL, SLT, SLTU, XOR, SRL, SRA, OR, AND)
            7'b0110011: begin
                regWrite_D = 1; alu_srcB_D = 0;
                case (funct3)
                    3'b000: alu_ctrl = (funct7[5]) ? ALU_SUB : ALU_ADD;
                    3'b001: alu_ctrl = ALU_SLL;
                    3'b010: alu_ctrl = ALU_SLT;
                    3'b011: alu_ctrl = ALU_SLTU;
                    3'b100: alu_ctrl = ALU_XOR;
                    3'b101: alu_ctrl = (funct7[5]) ? ALU_SRA : ALU_SRL;
                    3'b110: alu_ctrl = ALU_OR;
                    3'b111: alu_ctrl = ALU_AND;
                endcase
            end
        endcase
    end
endmodule

testbench/control_unit_tb.v
`timescale 1ns/1ps

module control_unit_tb;
    reg [6:0] opcode;
    reg [2:0] funct3;
    reg [6:0] funct7;
    wire regWrite_D;
    wire [2:0] imm_sel;
    wire alu_srcA_D;
    wire alu_srcB_D;
    wire [9:0] alu_ctrl;
    wire branch_D;
    wire [2:0] bropcode;
    wire [1:0] jump_D;
    wire [2:0] load_sel_D;
    wire [2:0] store_sel_D;
    wire memWrite_D;
    wire [1:0] write_back_D;

    control_unit uut (
        .opcode(opcode),
        .funct3(funct3),
        .funct7(funct7),
        .regWrite_D(regWrite_D),
        .imm_sel(imm_sel),
        .alu_srcA_D(alu_srcA_D),
        .alu_srcB_D(alu_srcB_D),
        .alu_ctrl(alu_ctrl),
        .branch_D(branch_D),
        .bropcode(bropcode),
        .jump_D(jump_D),
        .load_sel_D(load_sel_D),
        .store_sel_D(store_sel_D),
        .memWrite_D(memWrite_D),
        .write_back_D(write_back_D)
    );

    task check;
        input [8*16-1:0] name;
        input [1:0] expect_wb;
        begin
            #5;
            if (write_back_D !== expect_wb) $display("ERROR %s: write_back_D=%b expected=%b", name, write_back_D, expect_wb);
            $display("%s: opcode=%b funct3=%b funct7=%b -> regWrite=%b branch=%b jump=%b alu_ctrl=%b", name, opcode, funct3, funct7, regWrite_D, branch_D, jump_D, alu_ctrl);
        end
    endtask

    initial begin
        $dumpfile("mophong_vcd/control_unit_tb.vcd");
        $dumpvars(0, control_unit_tb);

        opcode = 7'b0110111; funct3 = 3'b000; funct7 = 7'b0000000; // LUI
        check("LUI", 2'b00);

        opcode = 7'b0010111; check("AUIPC", 2'b00);

        opcode = 7'b1101111; check("JAL", 2'b10);

        opcode = 7'b1100111; funct3 = 3'b000; funct7 = 7'b0000000; check("JALR", 2'b10);

        opcode = 7'b1100011; funct3 = 3'b000; check("BEQ", 2'b00);

        opcode = 7'b0000011; funct3 = 3'b010; check("LW", 2'b01);

        opcode = 7'b0100011; funct3 = 3'b010; check("SW", 2'b00);

        opcode = 7'b0010011; funct3 = 3'b000; funct7 = 7'b0000000; check("ADDI", 2'b00);

        opcode = 7'b0110011; funct3 = 3'b000; funct7 = 7'b0000000; check("ADD", 2'b00);
        opcode = 7'b0110011; funct3 = 3'b000; funct7 = 7'b0100000; check("SUB", 2'b00);

        $display("control_unit_tb finished");
        $finish;
    end
endmodule

mophong_vcd/control_unit_tb.vcd
$date
	Fri Apr 17 23:04:21 2026
$end
$version
	Icarus Verilog
$end
$timescale
	1ps
$end
$scope module control_unit_tb $end
$var wire 2 ! write_back_D [1:0] $end
$var wire 3 " store_sel_D [2:0] $end
$var wire 1 # regWrite_D $end
$var wire 1 $ memWrite_D $end
$var wire 3 % load_sel_D [2:0] $end
$var wire 2 & jump_D [1:0] $end
$var wire 3 ' imm_sel [2:0] $end
$var wire 3 ( bropcode [2:0] $end
$var wire 1 ) branch_D $end
$var wire 1 * alu_srcB_D $end
$var wire 1 + alu_srcA_D $end
$var wire 10 , alu_ctrl [9:0] $end
$var reg 3 - funct3 [2:0] $end
$var reg 7 . funct7 [6:0] $end
$var reg 7 / opcode [6:0] $end
$scope module uut $end
$var wire 3 0 funct3 [2:0] $end
$var wire 7 1 funct7 [6:0] $end
$var wire 7 2 opcode [6:0] $end
$var parameter 10 3 ALU_ADD $end
$var parameter 10 4 ALU_AND $end
$var parameter 10 5 ALU_OR $end
$var parameter 10 6 ALU_SLL $end
$var parameter 10 7 ALU_SLT $end
$var parameter 10 8 ALU_SLTU $end
$var parameter 10 9 ALU_SRA $end
$var parameter 10 : ALU_SRL $end
$var parameter 10 ; ALU_SUB $end
$var parameter 10 < ALU_XOR $end
$var reg 10 = alu_ctrl [9:0] $end
$var reg 1 + alu_srcA_D $end
$var reg 1 * alu_srcB_D $end
$var reg 1 ) branch_D $end
$var reg 3 > bropcode [2:0] $end
$var reg 3 ? imm_sel [2:0] $end
$var reg 2 @ jump_D [1:0] $end
$var reg 3 A load_sel_D [2:0] $end
$var reg 1 $ memWrite_D $end
$var reg 1 # regWrite_D $end
$var reg 3 B store_sel_D [2:0] $end
$var reg 2 C write_back_D [1:0] $end
$upscope $end
$scope task check $end
$var reg 2 D expect_wb [1:0] $end
$var reg 128 E name [127:0] $end
$upscope $end
$upscope $end
$enddefinitions $end
$comment Show the parameter values. $end
$dumpall
b100000 <
b10 ;
b1000000 :
b10000000 9
b10000 8
b1000 7
b100 6
b100000000 5
b1000000000 4
b1 3
$end
#0
$dumpvars
b10011000101010101001001 E
b0 D
b0 C
b10 B
b10 A
b0 @
b11 ?
b0 >
b1 =
b110111 2
b0 1
b0 0
b110111 /
b0 .
b0 -
b1 ,
0+
1*
0)
b0 (
b11 '
b0 &
b10 %
0$
1#
b10 "
b0 !
$end
#5000
1+
1*
b11 '
b11 ?
1#
b100000101010101010010010101000001000011 E
b10111 /
b10111 2
#10000
b10 !
b10 C
b1 &
b1 @
0*
0+
b100 '
b100 ?
1#
b10 D
b10010100100000101001100 E
b1101111 /
b1101111 2
#15000
1*
b10 !
b10 C
b10 &
b10 @
b0 '
b0 ?
1#
b1001010010000010100110001010010 E
b1100111 /
b1100111 2
#20000
b10 ,
b10 =
b10 '
b10 ?
1)
b0 !
b0 C
b0 &
b0 @
0*
0#
b0 D
b10000100100010101010001 E
b1100011 /
b1100011 2
#25000
b1 !
b1 C
1*
1#
0)
b1 ,
b1 =
b0 '
b0 ?
b1 D
b100110001010111 E
b10 -
b10 0
b11 /
b11 2
#30000
b1 '
b1 ?
1$
b0 !
b0 C
1*
0#
b0 D
b101001101010111 E
b100011 /
b100011 2
#35000
1#
0$
1*
b0 '
b0 ?
b1000001010001000100010001001001 E
b0 -
b0 0
b10011 /
b10011 2
#40000
0*
1#
b10000010100010001000100 E
b110011 /
b110011 2
#45000
b10 ,
b10 =
1#
b10100110101010101000010 E
b100000 .
b100000 1
