src/control_unit.v
module control_unit (
    input wire [6:0] opcode,
    input wire [2:0] funct3,
    input wire [6:0] funct7, 

    output reg        regWrite_D,   
    output reg [2:0]  imm_sel,      
    output reg        alu_srcA_D,   
    output reg        alu_srcB_D,   
    output reg [3:0]  alu_ctrl,     
    output reg        branch_D,     
    output reg [2:0]  bropcode,     
    output reg [1:0]  jump_D,       // 01: JAL, 10: JALR, 00: No Jump
    output reg [2:0]  load_sel_D,   
    output reg [2:0]  store_sel_D,  // ĐÃ SỬA: Xóa dấu & lỗi cú pháp ở đây
    output reg        memWrite_D,   
    output reg [1:0]  write_back_D, 
    output reg        uses_rs1_D,   
    output reg        uses_rs2_D    
);

    // Định nghĩa hằng số ALU 4-bit mã hóa
    localparam ALU_ADD  = 4'b0000;
    localparam ALU_SUB  = 4'b0001;
    localparam ALU_SLL  = 4'b0010;
    localparam ALU_SLT  = 4'b0011;
    localparam ALU_SLTU = 4'b0100;
    localparam ALU_XOR  = 4'b0101;
    localparam ALU_SRL  = 4'b0110;
    localparam ALU_SRA  = 4'b0111;
    localparam ALU_OR   = 4'b1000;
    localparam ALU_AND  = 4'b1001;
    localparam ALU_LUI  = 4'b1010; 

    always @(*) begin
        // --- Giá trị mặc định tránh tạo chốt lật (Latch generation) ---
        regWrite_D   = 0; 
        imm_sel      = 3'b000; 
        alu_srcA_D   = 0; 
        alu_srcB_D   = 0;
        alu_ctrl     = ALU_ADD; 
        branch_D     = 0; 
        bropcode     = 3'b000; 
        jump_D       = 2'b00;
        load_sel_D   = 3'b010; 
        store_sel_D  = 3'b010; 
        memWrite_D   = 0; 
        write_back_D = 2'b00;
        uses_rs1_D   = 1'b0; 
        uses_rs2_D   = 1'b0;

        case (opcode)
            // 1. LUI
            7'b0110111: begin
                regWrite_D   = 1; 
                imm_sel      = 3'b011; 
                alu_srcB_D   = 1;
                alu_ctrl     = ALU_LUI; 
                write_back_D = 2'b00;
            end

            // 2. AUIPC
            7'b0010111: begin
                regWrite_D   = 1; 
                imm_sel      = 3'b011; 
                alu_srcA_D   = 1; 
                alu_srcB_D   = 1;
                alu_ctrl     = ALU_ADD; 
                write_back_D = 2'b00;
            end

            // 3. JAL
            7'b1101111: begin
                regWrite_D   = 1; 
                imm_sel      = 3'b100; 
                jump_D       = 2'b01; // Đánh dấu lệnh JAL nhảy không điều kiện
                write_back_D = 2'b10; 
            end

            // 4. JALR
            7'b1100111: begin
                regWrite_D   = 1; 
                imm_sel      = 3'b000; 
                jump_D       = 2'b10; // Đánh dấu lệnh JALR
                alu_srcB_D   = 1; 
                alu_ctrl     = ALU_ADD; 
                write_back_D = 2'b10;
                uses_rs1_D   = 1'b1;
            end

            // 5. BRANCH (BEQ, BNE, BLT, BGE, BLTU, BGEU)
            7'b1100011: begin
                branch_D   = 1; 
                imm_sel    = 3'b010; 
                bropcode   = funct3; // Đưa thẳng funct3 ra để phân loại kiểu so sánh nhánh
                alu_ctrl   = (funct3[2:1] == 2'b11) ? ALU_SLTU : ALU_SUB; 
                uses_rs1_D = 1'b1; 
                uses_rs2_D = 1'b1;
            end

            // 6. LOAD
            7'b0000011: begin
                regWrite_D   = 1; 
                imm_sel      = 3'b000; 
                alu_srcB_D   = 1;
                alu_ctrl     = ALU_ADD; 
                load_sel_D   = funct3; 
                write_back_D = 2'b01;
                uses_rs1_D   = 1'b1;
            end

            // 7. STORE
            7'b0100011: begin
                memWrite_D  = 1; 
                imm_sel     = 3'b001; 
                alu_srcB_D  = 1;
                alu_ctrl    = ALU_ADD; 
                store_sel_D = funct3;
                uses_rs1_D  = 1'b1; 
                uses_rs2_D  = 1'b1;
            end

            // 8. I-Type ALU
            7'b0010011: begin
                regWrite_D = 1; 
                alu_srcB_D = 1; 
                imm_sel    = 3'b000;
                uses_rs1_D = 1'b1;
                case (funct3)
                    3'b000: alu_ctrl = ALU_ADD;
                    3'b010: alu_ctrl = ALU_SLT;
                    3'b011: alu_ctrl = ALU_SLTU;
                    3'b100: alu_ctrl = ALU_XOR;
                    3'b110: alu_ctrl = ALU_OR;
                    3'b111: alu_ctrl = ALU_AND;
                    3'b001: alu_ctrl = ALU_SLL;
                    3'b101: alu_ctrl = (funct7[5]) ? ALU_SRA : ALU_SRL;
                endcase
            end

            // 9. R-Type ALU
            7'b0110011: begin
                regWrite_D = 1; 
                alu_srcB_D = 0;
                uses_rs1_D = 1'b1; 
                uses_rs2_D = 1'b1;
                case (funct3)
                    3'b000: alu_ctrl = (funct7[5]) ? ALU_SUB : ALU_ADD;
                    3'b001: alu_ctrl = ALU_SLL;
                    3'b010: alu_ctrl = ALU_SLT;
                    3'b011: alu_ctrl = ALU_SLTU;
                    3'b100: alu_ctrl = ALU_XOR;
                    3'b101: alu_ctrl = (funct7[5]) ? ALU_SRA : ALU_SRL;
                    3'b110: alu_ctrl = ALU_OR;
                    3'b111: alu_ctrl = ALU_AND;
                endcase
            end
            default: ;
        endcase
    end
endmodule

testbench/control_unit_tb.v
`timescale 1ns/1ps

module control_unit_tb;
    reg [6:0] opcode;
    reg [2:0] funct3;
    reg [6:0] funct7;
    wire regWrite_D;
    wire [2:0] imm_sel;
    wire alu_srcA_D;
    wire alu_srcB_D;
    wire [10:0] alu_ctrl;
    wire branch_D;
    wire [2:0] bropcode;
    wire [1:0] jump_D;
    wire [2:0] load_sel_D;
    wire [2:0] store_sel_D;
    wire memWrite_D;
    wire [1:0] write_back_D;

    control_unit uut (
        .opcode(opcode),
        .funct3(funct3),
        .funct7(funct7),
        .regWrite_D(regWrite_D),
        .imm_sel(imm_sel),
        .alu_srcA_D(alu_srcA_D),
        .alu_srcB_D(alu_srcB_D),
        .alu_ctrl(alu_ctrl),
        .branch_D(branch_D),
        .bropcode(bropcode),
        .jump_D(jump_D),
        .load_sel_D(load_sel_D),
        .store_sel_D(store_sel_D),
        .memWrite_D(memWrite_D),
        .write_back_D(write_back_D)
    );

    task check;
        input [8*16-1:0] name;
        input [1:0] expect_wb;
        begin
            #5;
            if (write_back_D !== expect_wb) $display("ERROR %s: write_back_D=%b expected=%b", name, write_back_D, expect_wb);
            $display("%s: opcode=%b funct3=%b funct7=%b -> regWrite=%b branch=%b jump=%b alu_ctrl=%b", name, opcode, funct3, funct7, regWrite_D, branch_D, jump_D, alu_ctrl);
        end
    endtask

    initial begin
        $dumpfile("mophong_vcd/control_unit_tb.vcd");
        $dumpvars(0, control_unit_tb);
        $monitor("t=%0t opcode=%b funct3=%b funct7=%b regWrite=%b branch=%b jump=%b alu_ctrl=%b wb=%b",
                 $time, opcode, funct3, funct7, regWrite_D, branch_D, jump_D, alu_ctrl, write_back_D);

        opcode = 7'b0110111; funct3 = 3'b000; funct7 = 7'b0000000; // LUI
        check("LUI", 2'b00);

        opcode = 7'b0010111; check("AUIPC", 2'b00);

        opcode = 7'b1101111; check("JAL", 2'b10);

        opcode = 7'b1100111; funct3 = 3'b000; funct7 = 7'b0000000; check("JALR", 2'b10);

        opcode = 7'b1100011; funct3 = 3'b000; check("BEQ", 2'b00);

        opcode = 7'b0000011; funct3 = 3'b010; check("LW", 2'b01);

        opcode = 7'b0100011; funct3 = 3'b010; check("SW", 2'b00);

        opcode = 7'b0010011; funct3 = 3'b000; funct7 = 7'b0000000; check("ADDI", 2'b00);

        opcode = 7'b0110011; funct3 = 3'b000; funct7 = 7'b0000000; check("ADD", 2'b00);
        opcode = 7'b0110011; funct3 = 3'b000; funct7 = 7'b0100000; check("SUB", 2'b00);

        $display("control_unit_tb finished");
        $finish;
    end
endmodule

mophong_vcd/control_unit_tb.vcd
$date
	Mon Jun  8 23:44:17 2026
$end
$version
	Icarus Verilog
$end
$timescale
	1ps
$end
$scope module control_unit_tb $end
$var wire 2 ! write_back_D [1:0] $end
$var wire 3 " store_sel_D [2:0] $end
$var wire 1 # regWrite_D $end
$var wire 1 $ memWrite_D $end
$var wire 3 % load_sel_D [2:0] $end
$var wire 2 & jump_D [1:0] $end
$var wire 3 ' imm_sel [2:0] $end
$var wire 3 ( bropcode [2:0] $end
$var wire 1 ) branch_D $end
$var wire 1 * alu_srcB_D $end
$var wire 1 + alu_srcA_D $end
$var wire 11 , alu_ctrl [10:0] $end
$var reg 3 - funct3 [2:0] $end
$var reg 7 . funct7 [6:0] $end
$var reg 7 / opcode [6:0] $end
$scope module uut $end
$var wire 3 0 funct3 [2:0] $end
$var wire 7 1 funct7 [6:0] $end
$var wire 7 2 opcode [6:0] $end
$var parameter 4 3 ALU_ADD $end
$var parameter 4 4 ALU_AND $end
$var parameter 4 5 ALU_LUI $end
$var parameter 4 6 ALU_OR $end
$var parameter 4 7 ALU_SLL $end
$var parameter 4 8 ALU_SLT $end
$var parameter 4 9 ALU_SLTU $end
$var parameter 4 : ALU_SRA $end
$var parameter 4 ; ALU_SRL $end
$var parameter 4 < ALU_SUB $end
$var parameter 4 = ALU_XOR $end
$var reg 4 > alu_ctrl [3:0] $end
$var reg 1 + alu_srcA_D $end
$var reg 1 * alu_srcB_D $end
$var reg 1 ) branch_D $end
$var reg 3 ? bropcode [2:0] $end
$var reg 3 @ imm_sel [2:0] $end
$var reg 2 A jump_D [1:0] $end
$var reg 3 B load_sel_D [2:0] $end
$var reg 1 $ memWrite_D $end
$var reg 1 # regWrite_D $end
$var reg 3 C store_sel_D [2:0] $end
$var reg 1 D uses_rs1_D $end
$var reg 1 E uses_rs2_D $end
$var reg 2 F write_back_D [1:0] $end
$upscope $end
$scope task check $end
$var reg 2 G expect_wb [1:0] $end
$var reg 128 H name [127:0] $end
$upscope $end
$upscope $end
$enddefinitions $end
$comment Show the parameter values. $end
$dumpall
b101 =
b1 <
b110 ;
b111 :
b100 9
b11 8
b10 7
b1000 6
b1010 5
b1001 4
b0 3
$end
#0
$dumpvars
b10011000101010101001001 H
b0 G
b0 F
0E
0D
b10 C
b10 B
b0 A
b11 @
b0 ?
b1010 >
b110111 2
b0 1
b0 0
b110111 /
b0 .
b0 -
b1010 ,
0+
1*
0)
b0 (
b11 '
b0 &
b10 %
0$
1#
b10 "
b0 !
$end
#5000
1+
b0 ,
b0 >
1*
b11 '
b11 @
1#
b100000101010101010010010101000001000011 H
b10111 /
b10111 2
#10000
b10 !
b10 F
b1 &
b1 A
0*
0+
b100 '
b100 @
1#
b10 G
b10010100100000101001100 H
b1101111 /
b1101111 2
#15000
1D
1*
b10 !
b10 F
b10 &
b10 A
b0 '
b0 @
1#
b1001010010000010100110001010010 H
b1100111 /
b1100111 2
#20000
1E
b1 ,
b1 >
b10 '
b10 @
1)
1D
b0 !
b0 F
b0 &
b0 A
0*
0#
b0 G
b10000100100010101010001 H
b1100011 /
b1100011 2
#25000
b1 !
b1 F
1*
1#
0E
1D
0)
b0 ,
b0 >
b0 '
b0 @
b1 G
b100110001010111 H
b10 -
b10 0
b11 /
b11 2
#30000
1E
b1 '
b1 @
1$
1D
b0 !
b0 F
1*
0#
b0 G
b101001101010111 H
b100011 /
b100011 2
#35000
1#
0E
1D
0$
1*
b0 '
b0 @
b1000001010001000100010001001001 H
b0 -
b0 0
b10011 /
b10011 2
#40000
1E
1D
0*
1#
b10000010100010001000100 H
b110011 /
b110011 2
#45000
b1 ,
b1 >
1E
1D
1#
b10100110101010101000010 H
b100000 .
b100000 1
