src/data_memory.v
module data_memory (
    input wire clk,
    input wire mem_write,       
    input wire [31:0] addr,     
    input wire [31:0] write_data, 
    input wire [2:0] load_sel,  
    input wire [2:0] store_sel, 
    output reg [31:0] read_data, 
    input wire [9:0] debug_addr,
    output wire [31:0] debug_val 
);
    reg [31:0] ram [0:127]; 

    // --- LOGIC GHI ĐỒNG BỘ ---
    always @(posedge clk) begin
        if (mem_write) begin
            case (store_sel)
                3'b000: begin // SB
                    case (addr[1:0])
                        2'b00: ram[addr[8:2]][7:0]   <= write_data[7:0];
                        2'b01: ram[addr[8:2]][15:8]  <= write_data[7:0];
                        2'b10: ram[addr[8:2]][23:16] <= write_data[7:0];
                        2'b11: ram[addr[8:2]][31:24] <= write_data[7:0];
                    endcase
                end
                3'b001: begin // SH
                    if (addr[1] == 1'b0) ram[addr[8:2]][15:0]  <= write_data[15:0];
                    else                 ram[addr[8:2]][31:16] <= write_data[15:0];
                end
                3'b010: begin // SW
                    ram[addr[8:2]] <= write_data;
                end
            endcase
        end
    end

    assign debug_val = ram[debug_addr[6:0]];

    // --- LOGIC ĐỌC BẤT ĐỒNG BỘ (SỬA Ở ĐÂY) ---
    wire [31:0] raw_word = ram[addr[8:2]]; // Đọc trực tiếp ra luôn
    
    wire [7:0] byte_to_load;
    wire [15:0] half_to_load;

    // Chọn byte/half-word trực tiếp từ tín hiệu ngõ vào (không cần chốt)
    assign byte_to_load = (addr[1:0] == 2'b00) ? raw_word[7:0] :
                          (addr[1:0] == 2'b01) ? raw_word[15:8] :
                          (addr[1:0] == 2'b10) ? raw_word[23:16] : raw_word[31:24];
                          
    assign half_to_load = (addr[1] == 1'b0) ? raw_word[15:0] : raw_word[31:16];

    always @(*) begin
        case (load_sel)
            3'b000: read_data = {{24{byte_to_load[7]}}, byte_to_load};  // LB
            3'b001: read_data = {{16{half_to_load[15]}}, half_to_load}; // LH
            3'b010: read_data = raw_word;                               // LW
            3'b100: read_data = {24'b0, byte_to_load};                  // LBU
            3'b101: read_data = {16'b0, half_to_load};                  // LHU
            default: read_data = raw_word;
        endcase
    end
endmodule

testbench/data_memory_tb.v
`timescale 1ns/1ps

module data_memory_tb;
    reg clk;
    reg mem_write;
    reg [31:0] addr;
    reg [31:0] write_data;
    reg [2:0] load_sel;
    reg [2:0] store_sel;
    wire [31:0] read_data;

    data_memory uut (
        .clk(clk),
        .mem_write(mem_write),
        .addr(addr),
        .write_data(write_data),
        .load_sel(load_sel),
        .store_sel(store_sel),
        .read_data(read_data)
    );

    initial begin
        $dumpfile("mophong_vcd/data_memory_tb.vcd");
        $dumpvars(0, data_memory_tb);
        $monitor("t=%0t clk=%b mem_write=%b addr=%h write_data=%h load_sel=%b store_sel=%b read_data=%h",
                 $time, clk, mem_write, addr, write_data, load_sel, store_sel, read_data);

        clk = 0; mem_write = 0; addr = 32'h0000_0000; write_data = 32'hA5A5_A5A5;
        store_sel = 3'b010; load_sel = 3'b010;

        // Write SW at address 0
        #5 addr = 32'h0000_0000; write_data = 32'h1234_5678; store_sel = 3'b010; mem_write = 1;
        #10 mem_write = 0;

        // Write SH at address 4
        #5 addr = 32'h0000_0004; write_data = 32'h0000_ABCD; store_sel = 3'b001; mem_write = 1;
        #10 mem_write = 0;

        // Write SB at address 8
        #5 addr = 32'h0000_0008; write_data = 32'h0000_00EF; store_sel = 3'b000; mem_write = 1;
        #10 mem_write = 0;

        // Test LW from address 0
        #5 addr = 32'h0000_0000; load_sel = 3'b010;
        #1 if (read_data !== 32'h1234_5678) $display("ERROR LW: got %h", read_data);

        // Test LH sign-extend from address 4
        #5 addr = 32'h0000_0004; load_sel = 3'b001;
        #1 if (read_data !== 32'hFFFF_ABCD) $display("ERROR LH: got %h", read_data);

        // Test LHU zero-extend from address 4
        #5 load_sel = 3'b101;
        #1 if (read_data !== 32'h0000_ABCD) $display("ERROR LHU: got %h", read_data);

        // Test LB sign-extend from address 8
        #5 addr = 32'h0000_0008; load_sel = 3'b000;
        #1 if (read_data !== 32'hFFFF_FFEF) $display("ERROR LB: got %h", read_data);

        // Test LBU zero-extend from address 8
        #5 load_sel = 3'b100;
        #1 if (read_data !== 32'h0000_00EF) $display("ERROR LBU: got %h", read_data);

        $display("data_memory_tb finished");
        $finish;
    end

    always #5 clk = ~clk;
endmodule

mophong_vcd/data_memory_tb.vcd
$date
	Mon May 11 14:44:21 2026
$end
$version
	Icarus Verilog
$end
$timescale
	1ps
$end
$scope module data_memory_tb $end
$var wire 32 ! read_data [31:0] $end
$var reg 32 " addr [31:0] $end
$var reg 1 # clk $end
$var reg 3 $ load_sel [2:0] $end
$var reg 1 % mem_write $end
$var reg 3 & store_sel [2:0] $end
$var reg 32 ' write_data [31:0] $end
$scope module uut $end
$var wire 32 ( addr [31:0] $end
$var wire 1 # clk $end
$var wire 10 ) debug_addr [9:0] $end
$var wire 32 * debug_val [31:0] $end
$var wire 3 + load_sel [2:0] $end
$var wire 1 % mem_write $end
$var wire 32 , raw_word [31:0] $end
$var wire 3 - store_sel [2:0] $end
$var wire 32 . write_data [31:0] $end
$var reg 8 / byte_to_load [7:0] $end
$var reg 16 0 half_to_load [15:0] $end
$var reg 32 1 read_data [31:0] $end
$upscope $end
$upscope $end
$enddefinitions $end
$comment Show the parameter values. $end
$dumpall
$end
#0
$dumpvars
bx 1
bx 0
bx /
b10100101101001011010010110100101 .
b10 -
bx ,
b10 +
bx *
bz )
b0 (
b10100101101001011010010110100101 '
b10 &
0%
b10 $
0#
b0 "
bx !
$end
#5000
b10010001101000101011001111000 !
b10010001101000101011001111000 1
b101011001111000 0
b1111000 /
b10010001101000101011001111000 ,
1#
1%
b10010001101000101011001111000 '
b10010001101000101011001111000 .
#10000
0#
#15000
1#
0%
#20000
bx !
bx 1
bx 0
bx /
bx ,
0#
1%
b1 &
b1 -
b1010101111001101 '
b1010101111001101 .
b100 "
b100 (
#25000
bx1010101111001101 !
bx1010101111001101 1
b1010101111001101 0
b11001101 /
bx1010101111001101 ,
1#
#30000
0#
0%
#35000
bx11101111 !
bx11101111 1
bx11101111 0
b11101111 /
bx11101111 ,
1#
1%
b0 &
b0 -
b11101111 '
b11101111 .
b1000 "
b1000 (
#40000
0#
#45000
1#
0%
#50000
b10010001101000101011001111000 !
b10010001101000101011001111000 1
b101011001111000 0
b1111000 /
b10010001101000101011001111000 ,
0#
b0 "
b0 (
#55000
1#
#56000
b11111111111111111010101111001101 !
b11111111111111111010101111001101 1
b1010101111001101 0
b11001101 /
bx1010101111001101 ,
b1 $
b1 +
b100 "
b100 (
#60000
0#
#62000
b1010101111001101 !
b1010101111001101 1
b101 $
b101 +
#65000
1#
#68000
b11111111111111111111111111101111 !
b11111111111111111111111111101111 1
bx11101111 0
b11101111 /
bx11101111 ,
b0 $
b0 +
b1000 "
b1000 (
#70000
0#
#74000
b11101111 !
b11101111 1
b100 $
b100 +
