src/ID_EX.v
module ID_EX (
    input  wire        clk,
    input  wire        rst_n,
    input  wire        stall,
    input  wire        flush,
    
    // Đầu vào từ ID stage
    input  wire [31:0] id_pc,
    input  wire[31:0] id_pc_plus4,
    input  wire [31:0] id_rs1_data,
    input  wire [31:0] id_rs2_data,
    input  wire [31:0] id_imm,
    input  wire [4:0]  id_rd,
    input  wire [4:0]  id_rs1,
    input  wire [4:0]  id_rs2,
    
    // Tín hiệu điều khiển vào
    input  wire        id_regWrite,
    input  wire [2:0]  id_imm_sel,
    input  wire        id_alu_srcA,
    input  wire        id_alu_srcB,
    input  wire [3:0] id_alu_ctrl,
    input  wire        id_branch,
    input  wire [2:0]  id_bropcode,
    input  wire [1:0]  id_jump,
    input  wire[2:0]  id_load_sel,
    input  wire [2:0]  id_store_sel,
    input  wire        id_memWrite,
    input  wire [1:0]  id_write_back,
    
    // Đầu ra tới EX stage
    output reg[31:0] ex_pc,
    output reg  [31:0] ex_pc_plus4,
    output reg  [31:0] ex_rs1_data,
    output reg[31:0] ex_rs2_data,
    output reg  [31:0] ex_imm,
    output reg  [4:0]  ex_rd,
    output reg[4:0]  ex_rs1,
    output reg  [4:0]  ex_rs2,
    
    // Tín hiệu điều khiển ra
    output reg         ex_regWrite,
    output reg  [2:0]  ex_imm_sel,
    output reg         ex_alu_srcA,
    output reg         ex_alu_srcB,
    output reg[3:0] ex_alu_ctrl,
    output reg         ex_branch,
    output reg[2:0]  ex_bropcode,
    output reg  [1:0]  ex_jump,
    output reg  [2:0]  ex_load_sel,
    output reg  [2:0]  ex_store_sel,
    output reg         ex_memWrite,
    output reg  [1:0]  ex_write_back
);

    // Sử dụng 1 block tuần tự duy nhất để dễ tổng hợp và Verify
    always @(posedge clk or negedge rst_n) begin
        if (!rst_n) begin
            // Reset không đồng bộ (Asynchronous Reset)
            ex_pc         <= 32'h0;
            ex_pc_plus4   <= 32'h4;
            ex_rs1_data   <= 32'h0;
            ex_rs2_data   <= 32'h0;
            ex_imm        <= 32'h0;
            ex_rd         <= 5'b0;
            ex_rs1        <= 5'b0;
            ex_rs2        <= 5'b0;
            ex_regWrite   <= 1'b0;
            ex_imm_sel    <= 3'b0;
            ex_alu_srcA   <= 1'b0;
            ex_alu_srcB   <= 1'b0;
            ex_alu_ctrl   <= 4'b0;
            ex_branch     <= 1'b0;
            ex_bropcode   <= 3'b0;
            ex_jump       <= 2'b0;
            ex_load_sel   <= 3'b0;
            ex_store_sel  <= 3'b0;
            ex_memWrite   <= 1'b0;
            ex_write_back <= 2'b0;
        end 
        else if (flush) begin
            // Xóa đồng bộ (Synchronous Flush)
            ex_pc         <= 32'h0;
            ex_pc_plus4   <= 32'h4;
            ex_rs1_data   <= 32'h0;
            ex_rs2_data   <= 32'h0;
            ex_imm        <= 32'h0;
            ex_rd         <= 5'b0;
            ex_rs1        <= 5'b0;
            ex_rs2        <= 5'b0;
            ex_regWrite   <= 1'b0;
            ex_imm_sel    <= 3'b0;
            ex_alu_srcA   <= 1'b0;
            ex_alu_srcB   <= 1'b0;
            ex_alu_ctrl   <= 4'b0;
            ex_branch     <= 1'b0;
            ex_bropcode   <= 3'b0;
            ex_jump       <= 2'b0;
            ex_load_sel   <= 3'b0;
            ex_store_sel  <= 3'b0;
            ex_memWrite   <= 1'b0;
            ex_write_back <= 2'b0;
        end 
        else if (!stall) begin
            // Chỉ cập nhật giá trị mới khi không bị Stall (Clock Enable)
            ex_pc         <= id_pc;
            ex_pc_plus4   <= id_pc_plus4;
            ex_rs1_data   <= id_rs1_data;
            ex_rs2_data   <= id_rs2_data;
            ex_imm        <= id_imm;
            ex_rd         <= id_rd;
            ex_rs1        <= id_rs1;
            ex_rs2        <= id_rs2;
            ex_regWrite   <= id_regWrite;
            ex_imm_sel    <= id_imm_sel;
            ex_alu_srcA   <= id_alu_srcA;
            ex_alu_srcB   <= id_alu_srcB;
            ex_alu_ctrl   <= id_alu_ctrl;
            ex_branch     <= id_branch;
            ex_bropcode   <= id_bropcode;
            ex_jump       <= id_jump;
            ex_load_sel   <= id_load_sel;
            ex_store_sel  <= id_store_sel;
            ex_memWrite   <= id_memWrite;
            ex_write_back <= id_write_back;
        end
        // Lưu ý: Nếu stall == 1 và flush == 0, Flip-flop sẽ tự động giữ nguyên giá trị cũ (không cần viết logic giữ).
    end

endmodule

testbench/ID_EX_tb.v
// Testbench cho ID_EX Pipeline Register

`timescale 1ns / 1ps

module ID_EX_tb;

    reg        clk;
    reg        rst_n;
    reg        stall;
    reg        flush;
    
    reg [31:0] id_pc;
    reg [31:0] id_pc_plus4;
    reg [31:0] id_rs1_data;
    reg [31:0] id_rs2_data;
    reg [31:0] id_imm;
    reg [4:0]  id_rd;
    reg [4:0]  id_rs1;
    reg [4:0]  id_rs2;
    
    reg        id_regWrite;
    reg [2:0]  id_imm_sel;
    reg        id_alu_srcA;
    reg        id_alu_srcB;
    reg [10:0] id_alu_ctrl;
    reg        id_branch;
    reg [2:0]  id_bropcode;
    reg [1:0]  id_jump;
    reg [2:0]  id_load_sel;
    reg [2:0]  id_store_sel;
    reg        id_memWrite;
    reg [1:0]  id_write_back;
    
    wire [31:0] ex_pc;
    wire [31:0] ex_pc_plus4;
    wire [31:0] ex_rs1_data;
    wire [31:0] ex_rs2_data;
    wire [31:0] ex_imm;
    wire [4:0]  ex_rd;
    wire [4:0]  ex_rs1;
    wire [4:0]  ex_rs2;
    
    wire        ex_regWrite;
    wire [2:0]  ex_imm_sel;
    wire        ex_alu_srcA;
    wire        ex_alu_srcB;
    wire [10:0] ex_alu_ctrl;
    wire        ex_branch;
    wire [2:0]  ex_bropcode;
    wire [1:0]  ex_jump;
    wire [2:0]  ex_load_sel;
    wire [2:0]  ex_store_sel;
    wire        ex_memWrite;
    wire [1:0]  ex_write_back;

    // Instantiate the module
    ID_EX uut (
        .clk(clk),
        .rst_n(rst_n),
        .stall(stall),
        .flush(flush),
        .id_pc(id_pc),
        .id_pc_plus4(id_pc_plus4),
        .id_rs1_data(id_rs1_data),
        .id_rs2_data(id_rs2_data),
        .id_imm(id_imm),
        .id_rd(id_rd),
        .id_rs1(id_rs1),
        .id_rs2(id_rs2),
        .id_regWrite(id_regWrite),
        .id_imm_sel(id_imm_sel),
        .id_alu_srcA(id_alu_srcA),
        .id_alu_srcB(id_alu_srcB),
        .id_alu_ctrl(id_alu_ctrl),
        .id_branch(id_branch),
        .id_bropcode(id_bropcode),
        .id_jump(id_jump),
        .id_load_sel(id_load_sel),
        .id_store_sel(id_store_sel),
        .id_memWrite(id_memWrite),
        .id_write_back(id_write_back),
        .ex_pc(ex_pc),
        .ex_pc_plus4(ex_pc_plus4),
        .ex_rs1_data(ex_rs1_data),
        .ex_rs2_data(ex_rs2_data),
        .ex_imm(ex_imm),
        .ex_rd(ex_rd),
        .ex_rs1(ex_rs1),
        .ex_rs2(ex_rs2),
        .ex_regWrite(ex_regWrite),
        .ex_imm_sel(ex_imm_sel),
        .ex_alu_srcA(ex_alu_srcA),
        .ex_alu_srcB(ex_alu_srcB),
        .ex_alu_ctrl(ex_alu_ctrl),
        .ex_branch(ex_branch),
        .ex_bropcode(ex_bropcode),
        .ex_jump(ex_jump),
        .ex_load_sel(ex_load_sel),
        .ex_store_sel(ex_store_sel),
        .ex_memWrite(ex_memWrite),
        .ex_write_back(ex_write_back)
    );

    // Clock generation
    initial begin
        clk = 0;
        forever #5 clk = ~clk;  // 10ns clock period
    end

    // Test cases
    initial begin
        $dumpfile("mophong_vcd/ID_EX_tb.vcd");
        $dumpvars(0, ID_EX_tb);
        
        // Khởi tạo
        rst_n = 0;
        stall = 0;
        flush = 0;
        id_pc = 32'h0000_0000;
        id_pc_plus4 = 32'h0000_0004;
        id_rs1_data = 32'h0000_0000;
        id_rs2_data = 32'h0000_0000;
        id_imm = 32'h0000_0000;
        id_rd = 5'b0_0001;
        id_rs1 = 5'b0_0000;
        id_rs2 = 5'b0_0000;
        id_regWrite = 1'b0;
        id_imm_sel = 3'b000;
        id_alu_srcA = 1'b0;
        id_alu_srcB = 1'b0;
        id_alu_ctrl = 11'b000_0000_0000;
        id_branch = 1'b0;
        id_bropcode = 3'b000;
        id_jump = 2'b00;
        id_load_sel = 3'b000;
        id_store_sel = 3'b000;
        id_memWrite = 1'b0;
        id_write_back = 2'b00;
        
        #10 rst_n = 1;  // Release reset
        
        // Test 1: Ghi dữ liệu bình thường (lệnh ADDI x1, x0, 1)
        $display("=== TEST 1: Ghi dữ liệu lệnh ADDI ===");
        id_pc = 32'h0000_0000;
        id_pc_plus4 = 32'h0000_0004;
        id_rs1_data = 32'h0000_0000;
        id_rs2_data = 32'h0000_0000;
        id_imm = 32'h0000_0001;  // immediate = 1
        id_rd = 5'b0_0001;       // rd = x1
        id_rs1 = 5'b0_0000;      // rs1 = x0
        id_regWrite = 1'b1;
        id_alu_srcA = 1'b0;
        id_alu_srcB = 1'b1;
        id_alu_ctrl = 11'b000_0000_0000;  // ADD operation
        id_write_back = 2'b00;
        #10;
        
        if (ex_pc !== 32'h0000_0000 || ex_rd !== 5'b0_0001 || ex_regWrite !== 1'b1) begin
            $display("FAIL: Dữ liệu không được cập nhật đúng");
        end else begin
            $display("PASS: ex_pc=%h, ex_rd=%d, ex_regWrite=%b", ex_pc, ex_rd, ex_regWrite);
        end
        
        // Test 2: Cập nhật lệnh tiếp theo (LW x2, 0(x1))
        $display("\n=== TEST 2: Ghi dữ liệu lệnh LW ===");
        id_pc = 32'h0000_0004;
        id_pc_plus4 = 32'h0000_0008;
        id_rs1_data = 32'h0000_0001;  // x1 = 1
        id_rs2_data = 32'h0000_0000;
        id_imm = 32'h0000_0000;       // offset = 0
        id_rd = 5'b0_0010;            // rd = x2
        id_rs1 = 5'b0_0001;           // rs1 = x1
        id_regWrite = 1'b1;
        id_alu_srcA = 1'b0;
        id_alu_srcB = 1'b1;
        id_alu_ctrl = 11'b000_0000_0000;
        id_load_sel = 3'b010;         // 32-bit load
        id_write_back = 2'b01;        // Memory data
        #10;
        
        if (ex_pc !== 32'h0000_0004 || ex_rd !== 5'b0_0010 || ex_load_sel !== 3'b010) begin
            $display("FAIL: Dữ liệu LW không đúng");
        end else begin
            $display("PASS: ex_pc=%h, ex_rd=%d, ex_load_sel=%b", ex_pc, ex_rd, ex_load_sel);
        end
        
        // Test 3: Stall - dữ liệu không thay đổi
        $display("\n=== TEST 3: Điều kiện Stall ===");
        stall = 1;
        id_pc = 32'h0000_0008;
        id_pc_plus4 = 32'h0000_000C;
        id_rd = 5'b0_0011;
        #10;
        
        if (ex_pc !== 32'h0000_0004 || ex_rd !== 5'b0_0010) begin
            $display("FAIL: Dữ liệu thay đổi trong lúc stall");
        end else begin
            $display("PASS: Dữ liệu được giữ nguyên (ex_pc=%h)", ex_pc);
        end
        
        // Test 4: Flush - xóa dữ liệu (NOP)
        $display("\n=== TEST 4: Điều kiện Flush ===");
        stall = 0;
        flush = 1;
        #10;
        
        if (ex_regWrite !== 1'b0 || ex_pc !== 32'h0000_0000) begin
            $display("FAIL: Flush không xóa dữ liệu đúng");
        end else begin
            $display("PASS: Đã flush (ex_regWrite=%b, ex_pc=%h)", ex_regWrite, ex_pc);
        end
        
        // Test 5: Tiếp tục sau flush (lệnh BEQ)
        $display("\n=== TEST 5: Tiếp tục sau flush với lệnh BEQ ===");
        flush = 0;
        id_pc = 32'h0000_0010;
        id_pc_plus4 = 32'h0000_0014;
        id_rs1_data = 32'h0000_0005;
        id_rs2_data = 32'h0000_0005;
        id_imm = 32'h0000_0010;       // branch offset
        id_rd = 5'b0_0000;            // rd = x0 (không cần ghi)
        id_regWrite = 1'b0;
        id_branch = 1'b1;
        id_bropcode = 3'b000;         // BEQ
        #10;
        
        if (ex_pc !== 32'h0000_0010 || ex_branch !== 1'b1) begin
            $display("FAIL: Lệnh BEQ không được cập nhật đúng");
        end else begin
            $display("PASS: ex_pc=%h, ex_branch=%b, rs1_data=%h, rs2_data=%h", 
                     ex_pc, ex_branch, ex_rs1_data, ex_rs2_data);
        end
        
        #20;
        $finish;
    end

endmodule

mophong_vcd/ID_EX_tb.vcd
$date
	Mon Jun  8 23:44:16 2026
$end
$version
	Icarus Verilog
$end
$timescale
	1ps
$end
$scope module ID_EX_tb $end
$var wire 2 ! ex_write_back [1:0] $end
$var wire 3 " ex_store_sel [2:0] $end
$var wire 32 # ex_rs2_data [31:0] $end
$var wire 5 $ ex_rs2 [4:0] $end
$var wire 32 % ex_rs1_data [31:0] $end
$var wire 5 & ex_rs1 [4:0] $end
$var wire 1 ' ex_regWrite $end
$var wire 5 ( ex_rd [4:0] $end
$var wire 32 ) ex_pc_plus4 [31:0] $end
$var wire 32 * ex_pc [31:0] $end
$var wire 1 + ex_memWrite $end
$var wire 3 , ex_load_sel [2:0] $end
$var wire 2 - ex_jump [1:0] $end
$var wire 3 . ex_imm_sel [2:0] $end
$var wire 32 / ex_imm [31:0] $end
$var wire 3 0 ex_bropcode [2:0] $end
$var wire 1 1 ex_branch $end
$var wire 1 2 ex_alu_srcB $end
$var wire 1 3 ex_alu_srcA $end
$var wire 11 4 ex_alu_ctrl [10:0] $end
$var reg 1 5 clk $end
$var reg 1 6 flush $end
$var reg 11 7 id_alu_ctrl [10:0] $end
$var reg 1 8 id_alu_srcA $end
$var reg 1 9 id_alu_srcB $end
$var reg 1 : id_branch $end
$var reg 3 ; id_bropcode [2:0] $end
$var reg 32 < id_imm [31:0] $end
$var reg 3 = id_imm_sel [2:0] $end
$var reg 2 > id_jump [1:0] $end
$var reg 3 ? id_load_sel [2:0] $end
$var reg 1 @ id_memWrite $end
$var reg 32 A id_pc [31:0] $end
$var reg 32 B id_pc_plus4 [31:0] $end
$var reg 5 C id_rd [4:0] $end
$var reg 1 D id_regWrite $end
$var reg 5 E id_rs1 [4:0] $end
$var reg 32 F id_rs1_data [31:0] $end
$var reg 5 G id_rs2 [4:0] $end
$var reg 32 H id_rs2_data [31:0] $end
$var reg 3 I id_store_sel [2:0] $end
$var reg 2 J id_write_back [1:0] $end
$var reg 1 K rst_n $end
$var reg 1 L stall $end
$scope module uut $end
$var wire 1 5 clk $end
$var wire 1 6 flush $end
$var wire 4 M id_alu_ctrl [3:0] $end
$var wire 1 8 id_alu_srcA $end
$var wire 1 9 id_alu_srcB $end
$var wire 1 : id_branch $end
$var wire 3 N id_bropcode [2:0] $end
$var wire 32 O id_imm [31:0] $end
$var wire 3 P id_imm_sel [2:0] $end
$var wire 2 Q id_jump [1:0] $end
$var wire 3 R id_load_sel [2:0] $end
$var wire 1 @ id_memWrite $end
$var wire 32 S id_pc [31:0] $end
$var wire 32 T id_pc_plus4 [31:0] $end
$var wire 5 U id_rd [4:0] $end
$var wire 1 D id_regWrite $end
$var wire 5 V id_rs1 [4:0] $end
$var wire 32 W id_rs1_data [31:0] $end
$var wire 5 X id_rs2 [4:0] $end
$var wire 32 Y id_rs2_data [31:0] $end
$var wire 3 Z id_store_sel [2:0] $end
$var wire 2 [ id_write_back [1:0] $end
$var wire 1 K rst_n $end
$var wire 1 L stall $end
$var reg 4 \ ex_alu_ctrl [3:0] $end
$var reg 1 3 ex_alu_srcA $end
$var reg 1 2 ex_alu_srcB $end
$var reg 1 1 ex_branch $end
$var reg 3 ] ex_bropcode [2:0] $end
$var reg 32 ^ ex_imm [31:0] $end
$var reg 3 _ ex_imm_sel [2:0] $end
$var reg 2 ` ex_jump [1:0] $end
$var reg 3 a ex_load_sel [2:0] $end
$var reg 1 + ex_memWrite $end
$var reg 32 b ex_pc [31:0] $end
$var reg 32 c ex_pc_plus4 [31:0] $end
$var reg 5 d ex_rd [4:0] $end
$var reg 1 ' ex_regWrite $end
$var reg 5 e ex_rs1 [4:0] $end
$var reg 32 f ex_rs1_data [31:0] $end
$var reg 5 g ex_rs2 [4:0] $end
$var reg 32 h ex_rs2_data [31:0] $end
$var reg 3 i ex_store_sel [2:0] $end
$var reg 2 j ex_write_back [1:0] $end
$upscope $end
$upscope $end
$enddefinitions $end
$comment Show the parameter values. $end
$dumpall
$end
#0
$dumpvars
b0 j
b0 i
b0 h
b0 g
b0 f
b0 e
b0 d
b100 c
b0 b
b0 a
b0 `
b0 _
b0 ^
b0 ]
b0 \
b0 [
b0 Z
b0 Y
b0 X
b0 W
b0 V
b1 U
b100 T
b0 S
b0 R
b0 Q
b0 P
b0 O
b0 N
b0 M
0L
0K
b0 J
b0 I
b0 H
b0 G
b0 F
b0 E
0D
b1 C
b100 B
b0 A
0@
b0 ?
b0 >
b0 =
b0 <
b0 ;
0:
09
08
b0 7
06
05
b0 4
03
02
01
b0 0
b0 /
b0 .
b0 -
b0 ,
0+
b0 *
b100 )
b0 (
0'
b0 &
b0 %
b0 $
b0 #
b0 "
b0 !
$end
#5000
15
#10000
05
19
1D
b1 <
b1 O
1K
#15000
12
1'
b1 (
b1 d
b1 /
b1 ^
15
#20000
05
b1 J
b1 [
b10 ?
b10 R
b1 E
b1 V
b10 C
b10 U
b0 <
b0 O
b1 F
b1 W
b1000 B
b1000 T
b100 A
b100 S
#25000
b1 !
b1 j
b10 ,
b10 a
b1 &
b1 e
b10 (
b10 d
b0 /
b0 ^
b1 %
b1 f
b1000 )
b1000 c
b100 *
b100 b
15
#30000
05
b11 C
b11 U
b1100 B
b1100 T
b1000 A
b1000 S
1L
#35000
15
#40000
05
16
0L
#45000
b0 !
b0 j
b0 ,
b0 a
02
0'
b0 &
b0 e
b0 (
b0 d
b0 %
b0 f
b100 )
b100 c
b0 *
b0 b
15
#50000
05
1:
0D
b0 C
b0 U
b10000 <
b10000 O
b101 H
b101 Y
b101 F
b101 W
b10100 B
b10100 T
b10000 A
b10000 S
06
#55000
b1 !
b1 j
b10 ,
b10 a
11
12
b1 &
b1 e
b10000 /
b10000 ^
b101 #
b101 h
b101 %
b101 f
b10100 )
b10100 c
b10000 *
b10000 b
15
