src/IF_ID.v
// IF_ID Pipeline Register (Instruction Fetch to Instruction Decode)
// Lưu trữ dữ liệu giữa giai đoạn IF và ID trong pipeline 5 tầng

module IF_ID (
    input wire        clk,
    input wire        rst_n,
    input wire        stall,      // Tín hiệu dừng pipeline (hazard từ Hazard Unit)
    input wire        flush,      // Tín hiệu xóa dữ liệu (khi có branch/jump)
    
    // Đầu vào từ IF stage
    input wire [31:0] if_pc,      // Program Counter từ IF stage
    input wire [31:0] if_pc_plus4,// PC + 4 từ IF stage
    input wire [31:0] if_instr,   // Instruction từ Instruction Memory
    
    // Đầu ra tới ID stage
    output reg [31:0] id_pc,      // Program Counter cho ID stage
    output reg [31:0] id_pc_plus4,// PC + 4 cho ID stage
    output reg [31:0] id_instr    // Instruction cho ID stage
);

    always @(posedge clk or negedge rst_n) begin
        if (!rst_n) begin
            // Khởi tạo toàn bộ register khi reset
            id_pc      <= 32'h0000_0000;
            id_pc_plus4 <= 32'h0000_0004;
            id_instr   <= 32'h0000_0013;  // NOP (addi x0, x0, 0)
        end
        else if (flush) begin
            // Xóa dữ liệu khi có branch/jump được thực thi
            id_pc      <= 32'h0000_0000;
            id_pc_plus4 <= 32'h0000_0004;
            id_instr   <= 32'h0000_0013;  // NOP
        end
        else if (!stall) begin
            // Cập nhật dữ liệu từ IF stage khi không bị stall
            id_pc      <= if_pc;
            id_pc_plus4 <= if_pc_plus4;
            id_instr   <= if_instr;
        end
        // Nếu stall = 1, giữ nguyên giá trị cũ
    end

endmodule

testbench/IF_ID_tb.v
// Testbench cho IF_ID Pipeline Register

`timescale 1ns / 1ps

module IF_ID_tb;

    reg        clk;
    reg        rst_n;
    reg        stall;
    reg        flush;
    reg [31:0] if_pc;
    reg [31:0] if_pc_plus4;
    reg [31:0] if_instr;
    
    wire [31:0] id_pc;
    wire [31:0] id_pc_plus4;
    wire [31:0] id_instr;

    // Instantiate the module
    IF_ID uut (
        .clk(clk),
        .rst_n(rst_n),
        .stall(stall),
        .flush(flush),
        .if_pc(if_pc),
        .if_pc_plus4(if_pc_plus4),
        .if_instr(if_instr),
        .id_pc(id_pc),
        .id_pc_plus4(id_pc_plus4),
        .id_instr(id_instr)
    );

    // Clock generation
    initial begin
        clk = 0;
        forever #5 clk = ~clk;  // 10ns clock period
    end

    // Test cases
    initial begin
        $dumpfile("mophong_vcd/IF_ID_tb.vcd");
        $dumpvars(0, IF_ID_tb);
        
        // Khởi tạo
        rst_n = 0;
        stall = 0;
        flush = 0;
        if_pc = 0;
        if_pc_plus4 = 4;
        if_instr = 32'h0000_0013;  // NOP
        
        #10 rst_n = 1;  // Release reset
        
        // Test 1: Ghi dữ liệu bình thường
        $display("=== TEST 1: Normal data write ===");
        if_pc = 32'h0000_0000;
        if_pc_plus4 = 32'h0000_0004;
        if_instr = 32'h0010_0093;  // addi x1, x0, 1
        #10;
        
        if (id_pc !== 32'h0000_0000 || id_instr !== 32'h0010_0093) begin
            $display("FAIL: Data not updated correctly");
        end else begin
            $display("PASS: id_pc = %h, id_instr = %h", id_pc, id_instr);
        end
        
        // Test 2: Cập nhật địa chỉ tiếp theo
        $display("\n=== TEST 2: Update to next instruction ===");
        if_pc = 32'h0000_0004;
        if_pc_plus4 = 32'h0000_0008;
        if_instr = 32'h0010_0113;  // addi x2, x0, 1
        #10;
        
        if (id_pc !== 32'h0000_0004 || id_instr !== 32'h0010_0113) begin
            $display("FAIL: Data not updated correctly");
        end else begin
            $display("PASS: id_pc = %h, id_instr = %h", id_pc, id_instr);
        end
        
        // Test 3: Stall - dữ liệu không thay đổi
        $display("\n=== TEST 3: Stall condition ===");
        stall = 1;
        if_pc = 32'h0000_0008;
        if_pc_plus4 = 32'h0000_000C;
        if_instr = 32'h0010_0193;  // addi x3, x0, 1
        #10;
        
        if (id_pc !== 32'h0000_0004 || id_instr !== 32'h0010_0113) begin
            $display("FAIL: Data changed during stall");
        end else begin
            $display("PASS: Data held during stall (id_pc = %h)", id_pc);
        end
        
        // Test 4: Flush - dữ liệu bị xóa (NOP)
        $display("\n=== TEST 4: Flush condition ===");
        stall = 0;
        flush = 1;
        #10;
        
        if (id_instr !== 32'h0000_0013) begin
            $display("FAIL: Flush didn't insert NOP");
        end else begin
            $display("PASS: Flushed with NOP (id_instr = %h)", id_instr);
        end
        
        // Test 5: Tiếp tục sau flush
        $display("\n=== TEST 5: Resume after flush ===");
        flush = 0;
        if_pc = 32'h0000_0010;
        if_pc_plus4 = 32'h0000_0014;
        if_instr = 32'h0020_0193;  // addi x3, x0, 2
        #10;
        
        if (id_pc !== 32'h0000_0010 || id_instr !== 32'h0020_0193) begin
            $display("FAIL: Data not updated after flush");
        end else begin
            $display("PASS: id_pc = %h, id_instr = %h", id_pc, id_instr);
        end
        
        #20;
        $finish;
    end

endmodule

mophong_vcd/IF_ID_tb.vcd
$date
	Thu Apr 23 15:23:56 2026
$end
$version
	Icarus Verilog
$end
$timescale
	1ps
$end
$scope module IF_ID_tb $end
$var wire 32 ! id_pc_plus4 [31:0] $end
$var wire 32 " id_pc [31:0] $end
$var wire 32 # id_instr [31:0] $end
$var reg 1 $ clk $end
$var reg 1 % flush $end
$var reg 32 & if_instr [31:0] $end
$var reg 32 ' if_pc [31:0] $end
$var reg 32 ( if_pc_plus4 [31:0] $end
$var reg 1 ) rst_n $end
$var reg 1 * stall $end
$scope module uut $end
$var wire 1 $ clk $end
$var wire 1 % flush $end
$var wire 32 + if_instr [31:0] $end
$var wire 32 , if_pc [31:0] $end
$var wire 32 - if_pc_plus4 [31:0] $end
$var wire 1 ) rst_n $end
$var wire 1 * stall $end
$var reg 32 . id_instr [31:0] $end
$var reg 32 / id_pc [31:0] $end
$var reg 32 0 id_pc_plus4 [31:0] $end
$upscope $end
$upscope $end
$enddefinitions $end
$comment Show the parameter values. $end
$dumpall
$end
#0
$dumpvars
b100 0
b0 /
b10011 .
b100 -
b0 ,
b10011 +
0*
0)
b100 (
b0 '
b10011 &
0%
0$
b10011 #
b0 "
b100 !
$end
#5000
1$
#10000
0$
b100000000000010010011 &
b100000000000010010011 +
1)
#15000
b100000000000010010011 #
b100000000000010010011 .
1$
#20000
0$
b100000000000100010011 &
b100000000000100010011 +
b1000 (
b1000 -
b100 '
b100 ,
#25000
b100000000000100010011 #
b100000000000100010011 .
b1000 !
b1000 0
b100 "
b100 /
1$
#30000
0$
b100000000000110010011 &
b100000000000110010011 +
b1100 (
b1100 -
b1000 '
b1000 ,
1*
#35000
1$
#40000
0$
1%
0*
#45000
b10011 #
b10011 .
b100 !
b100 0
b0 "
b0 /
1$
#50000
0$
b1000000000000110010011 &
b1000000000000110010011 +
b10100 (
b10100 -
b10000 '
b10000 ,
0%
#55000
b1000000000000110010011 #
b1000000000000110010011 .
b10100 !
b10100 0
b10000 "
b10000 /
1$
