src/MEM_WB.v
// MEM_WB Pipeline Register (Memory to Write Back)
// Lưu trữ dữ liệu giữa giai đoạn MEM và WB trong pipeline 5 tầng

module MEM_WB (
    input  wire        clk,
    input  wire        rst_n,
    
    // Đầu vào từ MEM stage
    input  wire[31:0] mem_pc_plus4,
    input  wire [31:0] mem_alu_result,
    input  wire [31:0] mem_mem_data,
    input  wire [4:0]  mem_rd,
    input  wire        mem_regWrite,
    input  wire [1:0]  mem_write_back,
    
    // Đầu ra tới WB stage
    output reg  [31:0] wb_pc_plus4,
    output reg  [31:0] wb_alu_result,
    output reg  [31:0] wb_mem_data,
    output reg  [4:0]  wb_rd,
    output reg         wb_regWrite,
    output reg  [1:0]  wb_write_back
);

    // --- 1. Logic tổ hợp: Chọn giá trị tiếp theo ---
    reg[31:0] next_wb_pc_plus4, next_wb_alu_result, next_wb_mem_data;
    reg [4:0]  next_wb_rd;
    reg        next_wb_regWrite;
    reg [1:0]  next_wb_write_back;

    always @(*) begin
        // Stage cuối không có stall hay flush, chỉ truyền dữ liệu qua
        next_wb_pc_plus4   = mem_pc_plus4;
        next_wb_alu_result = mem_alu_result;
        next_wb_mem_data   = mem_mem_data;
        next_wb_rd         = mem_rd;
        next_wb_regWrite   = mem_regWrite;
        next_wb_write_back = mem_write_back;
    end

    // --- 2. Logic tuần tự: Ghi vào thanh ghi ---
    always @(posedge clk or negedge rst_n) begin
        if (!rst_n) begin
            wb_pc_plus4   <= 32'h0000_0004;
            wb_alu_result <= 32'h0000_0000;
            wb_mem_data   <= 32'h0000_0000;
            wb_rd         <= 5'b00000;
            wb_regWrite   <= 1'b0;
            wb_write_back <= 2'b00;
        end 
        else begin
            wb_pc_plus4   <= next_wb_pc_plus4;
            wb_alu_result <= next_wb_alu_result;
            wb_mem_data   <= next_wb_mem_data;
            wb_rd         <= next_wb_rd;
            wb_regWrite   <= next_wb_regWrite;
            wb_write_back <= next_wb_write_back;
        end
    end

endmodule

testbench/MEM_WB_tb.v
// Testbench cho MEM_WB Pipeline Register

`timescale 1ns / 1ps

module MEM_WB_tb;

    reg        clk;
    reg        rst_n;
    
    reg [31:0] mem_pc_plus4;
    reg [31:0] mem_alu_result;
    reg [31:0] mem_mem_data;
    reg [4:0]  mem_rd;
    
    reg        mem_regWrite;
    reg [1:0]  mem_write_back;
    
    wire [31:0] wb_pc_plus4;
    wire [31:0] wb_alu_result;
    wire [31:0] wb_mem_data;
    wire [4:0]  wb_rd;
    
    wire        wb_regWrite;
    wire [1:0]  wb_write_back;

    // Instantiate the module
    MEM_WB uut (
        .clk(clk),
        .rst_n(rst_n),
        .mem_pc_plus4(mem_pc_plus4),
        .mem_alu_result(mem_alu_result),
        .mem_mem_data(mem_mem_data),
        .mem_rd(mem_rd),
        .mem_regWrite(mem_regWrite),
        .mem_write_back(mem_write_back),
        .wb_pc_plus4(wb_pc_plus4),
        .wb_alu_result(wb_alu_result),
        .wb_mem_data(wb_mem_data),
        .wb_rd(wb_rd),
        .wb_regWrite(wb_regWrite),
        .wb_write_back(wb_write_back)
    );

    // Clock generation
    initial begin
        clk = 0;
        forever #5 clk = ~clk;  // 10ns clock period
    end

    // Test cases
    initial begin
        $dumpfile("mophong_vcd/MEM_WB_tb.vcd");
        $dumpvars(0, MEM_WB_tb);
        $monitor("t=%0t clk=%b rst_n=%b mem_rd=%0d mem_regWrite=%b mem_wb_sel=%b wb_rd=%0d wb_regWrite=%b wb_alu=%h wb_mem=%h wb_pc4=%h",
                 $time, clk, rst_n, mem_rd, mem_regWrite, mem_write_back, wb_rd, wb_regWrite, wb_alu_result, wb_mem_data, wb_pc_plus4);
        
        // Khởi tạo
        rst_n = 0;
        mem_pc_plus4 = 32'h0000_0004;
        mem_alu_result = 32'h0000_0000;
        mem_mem_data = 32'h0000_0000;
        mem_rd = 5'b0_0000;
        mem_regWrite = 1'b0;
        mem_write_back = 2'b00;
        
        #10 rst_n = 1;  // Release reset
        
        // Test 1: Ghi dữ liệu lệnh ADD (write back ALU result)
        $display("=== TEST 1: Ghi dữ liệu lệnh ADD ===");
        mem_pc_plus4 = 32'h0000_0004;
        mem_alu_result = 32'h0000_000F;  // 10 + 5 = 15
        mem_mem_data = 32'h0000_0000;    // Không dùng
        mem_rd = 5'b0_0011;              // rd = x3
        mem_regWrite = 1'b1;
        mem_write_back = 2'b00;          // ALU result
        #10;
        
        if (wb_alu_result !== 32'h0000_000F || wb_rd !== 5'b0_0011 || wb_regWrite !== 1'b1) begin
            $display("FAIL: Dữ liệu ADD không đúng");
        end else begin
            $display("PASS: wb_alu_result=%h, wb_rd=%d, wb_regWrite=%b", wb_alu_result, wb_rd, wb_regWrite);
        end
        
        // Test 2: Ghi dữ liệu lệnh LW (write back memory data)
        $display("\n=== TEST 2: Ghi dữ liệu lệnh LW ===");
        mem_pc_plus4 = 32'h0000_0008;
        mem_alu_result = 32'h0000_0200;  // địa chỉ load (không dùng cho write back)
        mem_mem_data = 32'hABCD_1234;    // dữ liệu từ memory
        mem_rd = 5'b0_0100;              // rd = x4
        mem_regWrite = 1'b1;
        mem_write_back = 2'b01;          // Memory data
        #10;
        
        if (wb_mem_data !== 32'hABCD_1234 || wb_rd !== 5'b0_0100 || wb_write_back !== 2'b01) begin
            $display("FAIL: Dữ liệu LW không đúng");
        end else begin
            $display("PASS: wb_mem_data=%h, wb_rd=%d, wb_write_back=%b", wb_mem_data, wb_rd, wb_write_back);
        end
        
        // Test 3: Ghi dữ liệu lệnh JAL (write back PC+4)
        $display("\n=== TEST 3: Ghi dữ liệu lệnh JAL ===");
        mem_pc_plus4 = 32'h0000_0100;    // return address
        mem_alu_result = 32'h0000_0000;  // không dùng
        mem_mem_data = 32'h0000_0000;    // không dùng
        mem_rd = 5'b0_0001;              // rd = x1 (RA register)
        mem_regWrite = 1'b1;
        mem_write_back = 2'b10;          // PC + 4
        #10;
        
        if (wb_pc_plus4 !== 32'h0000_0100 || wb_rd !== 5'b0_0001 || wb_write_back !== 2'b10) begin
            $display("FAIL: Dữ liệu JAL không đúng");
        end else begin
            $display("PASS: wb_pc_plus4=%h, wb_rd=%d, wb_write_back=%b", wb_pc_plus4, wb_rd, wb_write_back);
        end
        
        // Test 4: Lệnh không ghi register (SW, BEQ, etc.)
        $display("\n=== TEST 4: Lệnh không ghi register ===");
        mem_pc_plus4 = 32'h0000_000C;
        mem_alu_result = 32'h0000_0300;
        mem_mem_data = 32'h0000_0000;
        mem_rd = 5'b0_0000;              // rd = x0
        mem_regWrite = 1'b0;             // Không ghi register
        mem_write_back = 2'b00;
        #10;
        
        if (wb_regWrite !== 1'b0) begin
            $display("FAIL: regWrite không đúng cho lệnh không ghi");
        end else begin
            $display("PASS: wb_regWrite=%b (không ghi register)", wb_regWrite);
        end
        
        // Test 5: Cập nhật liên tiếp
        $display("\n=== TEST 5: Cập nhật liên tiếp ===");
        mem_pc_plus4 = 32'h0000_0010;
        mem_alu_result = 32'h0000_FFFF;
        mem_mem_data = 32'h1234_5678;
        mem_rd = 5'b0_0101;              // rd = x5
        mem_regWrite = 1'b1;
        mem_write_back = 2'b01;          // Memory data
        #10;
        
        if (wb_mem_data !== 32'h1234_5678 || wb_rd !== 5'b0_0101) begin
            $display("FAIL: Cập nhật liên tiếp không đúng");
        end else begin
            $display("PASS: wb_mem_data=%h, wb_rd=%d", wb_mem_data, wb_rd);
        end
        
        #20;
        $finish;
    end

endmodule

mophong_vcd/MEM_WB_tb.vcd
$date
	Mon May 11 14:44:21 2026
$end
$version
	Icarus Verilog
$end
$timescale
	1ps
$end
$scope module MEM_WB_tb $end
$var wire 2 ! wb_write_back [1:0] $end
$var wire 1 " wb_regWrite $end
$var wire 5 # wb_rd [4:0] $end
$var wire 32 $ wb_pc_plus4 [31:0] $end
$var wire 32 % wb_mem_data [31:0] $end
$var wire 32 & wb_alu_result [31:0] $end
$var reg 1 ' clk $end
$var reg 32 ( mem_alu_result [31:0] $end
$var reg 32 ) mem_mem_data [31:0] $end
$var reg 32 * mem_pc_plus4 [31:0] $end
$var reg 5 + mem_rd [4:0] $end
$var reg 1 , mem_regWrite $end
$var reg 2 - mem_write_back [1:0] $end
$var reg 1 . rst_n $end
$scope module uut $end
$var wire 1 ' clk $end
$var wire 32 / mem_alu_result [31:0] $end
$var wire 32 0 mem_mem_data [31:0] $end
$var wire 32 1 mem_pc_plus4 [31:0] $end
$var wire 5 2 mem_rd [4:0] $end
$var wire 1 , mem_regWrite $end
$var wire 2 3 mem_write_back [1:0] $end
$var wire 1 . rst_n $end
$var reg 32 4 next_wb_alu_result [31:0] $end
$var reg 32 5 next_wb_mem_data [31:0] $end
$var reg 32 6 next_wb_pc_plus4 [31:0] $end
$var reg 5 7 next_wb_rd [4:0] $end
$var reg 1 8 next_wb_regWrite $end
$var reg 2 9 next_wb_write_back [1:0] $end
$var reg 32 : wb_alu_result [31:0] $end
$var reg 32 ; wb_mem_data [31:0] $end
$var reg 32 < wb_pc_plus4 [31:0] $end
$var reg 5 = wb_rd [4:0] $end
$var reg 1 " wb_regWrite $end
$var reg 2 > wb_write_back [1:0] $end
$upscope $end
$upscope $end
$enddefinitions $end
$comment Show the parameter values. $end
$dumpall
$end
#0
$dumpvars
b0 >
b0 =
b100 <
b0 ;
b0 :
b0 9
08
b0 7
b100 6
b0 5
b0 4
b0 3
b0 2
b100 1
b0 0
b0 /
0.
b0 -
0,
b0 +
b100 *
b0 )
b0 (
0'
b0 &
b0 %
b100 $
b0 #
0"
b0 !
$end
#5000
1'
#10000
18
b11 7
b1111 4
0'
1,
b11 +
b11 2
b1111 (
b1111 /
1.
#15000
1"
b11 #
b11 =
b1111 &
b1111 :
1'
#20000
b1 9
b100 7
b10101011110011010001001000110100 5
b1000000000 4
b1000 6
0'
b1 -
b1 3
b100 +
b100 2
b10101011110011010001001000110100 )
b10101011110011010001001000110100 0
b1000000000 (
b1000000000 /
b1000 *
b1000 1
#25000
b1 !
b1 >
b100 #
b100 =
b10101011110011010001001000110100 %
b10101011110011010001001000110100 ;
b1000000000 &
b1000000000 :
b1000 $
b1000 <
1'
#30000
b10 9
b1 7
b0 5
b0 4
b100000000 6
0'
b10 -
b10 3
b1 +
b1 2
b0 )
b0 0
b0 (
b0 /
b100000000 *
b100000000 1
#35000
b10 !
b10 >
b1 #
b1 =
b0 %
b0 ;
b0 &
b0 :
b100000000 $
b100000000 <
1'
#40000
b0 9
08
b0 7
b1100000000 4
b1100 6
0'
b0 -
b0 3
0,
b0 +
b0 2
b1100000000 (
b1100000000 /
b1100 *
b1100 1
#45000
b0 !
b0 >
0"
b0 #
b0 =
b1100000000 &
b1100000000 :
b1100 $
b1100 <
1'
#50000
b1 9
18
b101 7
b10010001101000101011001111000 5
b1111111111111111 4
b10000 6
0'
b1 -
b1 3
1,
b101 +
b101 2
b10010001101000101011001111000 )
b10010001101000101011001111000 0
b1111111111111111 (
b1111111111111111 /
b10000 *
b10000 1
#55000
b1 !
b1 >
1"
b101 #
b101 =
b10010001101000101011001111000 %
b10010001101000101011001111000 ;
b1111111111111111 &
b1111111111111111 :
b10000 $
b10000 <
1'
