src/Register_File.v
module Register_File (
    input wire clk,
    input wire rst_n,        // Tín hiệu reset hệ thống (tích cực mức thấp)
    input wire reg_write,    // Tín hiệu cho phép ghi từ tầng WB
    input wire [4:0] rs1,    // Địa chỉ nguồn 1 (từ tầng ID)
    input wire [4:0] rs2,    // Địa chỉ nguồn 2 (từ tầng ID)
    input wire [4:0] rd,     // Địa chỉ đích (từ tầng WB)
    input wire [31:0] wd,    // Dữ liệu ghi (từ tầng WB)
    output wire [31:0] rd1,  // Dữ liệu đọc ra 1
    output wire [31:0] rd2   // Dữ liệu đọc ra 2
);
    reg [31:0] rf [31:0];
    integer i;

    // Logic Ghi dữ liệu và Reset
    always @(posedge clk or negedge rst_n) begin
        if (!rst_n) begin
            // Khi reset, đưa tất cả 32 thanh ghi về giá trị 0
            for (i = 0; i < 32; i = i + 1) begin
                rf[i] <= 32'b0;
            end
        end 
        else if (reg_write && (rd != 5'b00000)) begin
            // Chỉ ghi khi có tín hiệu cho phép và không phải ghi vào thanh ghi x0
            rf[rd] <= wd;
        end
    end

    // Logic Đọc dữ liệu (Không đồng bộ - Asynchronous Read)
    // Theo kiến trúc RISC-V: thanh ghi x0 luôn luôn trả về giá trị 0
    assign rd1 = (reg_write && (rd == rs1) && (rs1 != 5'b0)) ? wd :
                 ((rs1 == 5'b0) ? 32'b0 : rf[rs1]);
    assign rd2 = (reg_write && (rd == rs2) && (rs2 != 5'b0)) ? wd :
                 ((rs2 == 5'b0) ? 32'b0 : rf[rs2]);

endmodule

testbench/Register_File_tb.v
`timescale 1ns/1ps

module Register_File_tb;
    reg clk;
    reg rst_n;
    reg reg_write;
    reg [4:0] rs1;
    reg [4:0] rs2;
    reg [4:0] rd;
    reg [31:0] wd;
    wire [31:0] rd1;
    wire [31:0] rd2;

    Register_File uut (
        .clk(clk),
        .rst_n(rst_n),
        .reg_write(reg_write),
        .rs1(rs1),
        .rs2(rs2),
        .rd(rd),
        .wd(wd),
        .rd1(rd1),
        .rd2(rd2)
    );

    initial begin
        $dumpfile("mophong_vcd/Register_File_tb.vcd");
        $dumpvars(0, Register_File_tb);

        clk = 0; rst_n = 0; reg_write = 0;
        rs1 = 5'd1; rs2 = 5'd2; rd = 5'd1; wd = 32'hDEAD_BEEF;
        #10 rst_n = 1;

        // Reset clears registers and x0 stays zero
        #10;
        if (rd1 !== 32'h0 || rd2 !== 32'h0) $display("ERROR RF reset: rd1=%h rd2=%h", rd1, rd2);

        // Write x1
        reg_write = 1; rd = 5'd1; wd = 32'h0000_1234; #10;
        rs1 = 5'd1; rs2 = 5'd0; #1;
        if (rd1 !== 32'h0000_1234) $display("ERROR RF write x1: got %h", rd1);
        if (rd2 !== 32'h0000_0000) $display("ERROR RF x0 read: expected 0 got %h", rd2);

        // Attempt to write x0 should not change x0
        reg_write = 1; rd = 5'd0; wd = 32'hFFFF_FFFF; #10;
        rs1 = 5'd0; rs2 = 5'd1; #1;
        if (rd1 !== 32'h0000_0000) $display("ERROR RF x0 write protection: got %h", rd1);
        if (rd2 !== 32'h0000_1234) $display("ERROR RF read x1 after x0 write: got %h", rd2);

        $display("Register_File_tb finished");
        $finish;
    end

    always #5 clk = ~clk;
endmodule

mophong_vcd/Register_File_tb.vcd
$date
	Fri Apr 17 23:04:21 2026
$end
$version
	Icarus Verilog
$end
$timescale
	1ps
$end
$scope module Register_File_tb $end
$var wire 32 ! rd2 [31:0] $end
$var wire 32 " rd1 [31:0] $end
$var reg 1 # clk $end
$var reg 5 $ rd [4:0] $end
$var reg 1 % reg_write $end
$var reg 5 & rs1 [4:0] $end
$var reg 5 ' rs2 [4:0] $end
$var reg 1 ( rst_n $end
$var reg 32 ) wd [31:0] $end
$scope module uut $end
$var wire 1 # clk $end
$var wire 5 * rd [4:0] $end
$var wire 1 % reg_write $end
$var wire 5 + rs1 [4:0] $end
$var wire 5 , rs2 [4:0] $end
$var wire 1 ( rst_n $end
$var wire 32 - wd [31:0] $end
$var wire 32 . rd2 [31:0] $end
$var wire 32 / rd1 [31:0] $end
$var integer 32 0 i [31:0] $end
$upscope $end
$upscope $end
$enddefinitions $end
$comment Show the parameter values. $end
$dumpall
$end
#0
$dumpvars
b100000 0
b0 /
b0 .
b11011110101011011011111011101111 -
b10 ,
b1 +
b1 *
b11011110101011011011111011101111 )
0(
b10 '
b1 &
0%
b1 $
0#
b0 "
b0 !
$end
#5000
b100000 0
1#
#10000
0#
1(
#15000
1#
#20000
0#
b1001000110100 )
b1001000110100 -
1%
#25000
b1001000110100 "
b1001000110100 /
1#
#30000
0#
b0 '
b0 ,
#31000
b11111111111111111111111111111111 )
b11111111111111111111111111111111 -
b0 $
b0 *
#35000
1#
#40000
0#
#41000
b1001000110100 !
b1001000110100 .
b0 "
b0 /
b1 '
b1 ,
b0 &
b0 +
